MANIFEST.in
readme.md
setup.py
OpenFOAM/__init__.py
OpenFOAM.egg-info/PKG-INFO
OpenFOAM.egg-info/SOURCES.txt
OpenFOAM.egg-info/dependency_links.txt
OpenFOAM.egg-info/entry_points.txt
OpenFOAM.egg-info/requires.txt
OpenFOAM.egg-info/top_level.txt