Metadata-Version: 1.0
Name: OpenFOAM
Version: 0.1.0
Summary: Python API of OpenFOAM, specially for the postprocess and data visualization
Home-page: https://gitlab.com/hydrothermal-openfoam/pyOpenFOAM
Author: Zhikui Guo
Author-email: zguo@geomar.de
License: UNKNOWN
Keywords: OpenFOAM publication figure SCI postprocessing
Platform: UNKNOWN
